Workbook

Sheet Assumptions
A1: INBOX-AGENT PRICING MODEL — ASSUMPTIONS
A2: Yellow = editable input. Change these; every other sheet recalcs.
A4: AI calls per email
A5: calls_per_email | B5: 2 | C5: Classifier + extractor (set to 1 if classifier is a heuristic)
A6: Token sizes (per email, summed across calls)
A7: tok_cached_in | B7: 1500 | C7: System prompt, served from cache after 1st call
A8: tok_fresh_in | B8: 1200 | C8: Email body (HTML-stripped) + classifier hint
A9: tok_output | B9: 250 | C9: Structured JSON result
A10: Claude (claude-sonnet-4-6) rates $/token
A11: rate_cache_read | B11: 3e-07 | C11: $0.30 / M tokens
A12: rate_input | B12: 3e-06 | C12: $3.00 / M tokens
A13: rate_output | B13: 1.5e-05 | C13: $15.00 / M tokens
A14: Gemini (gemini-2.0-flash) rates $/token
A15: g_rate_input | B15: 1e-07 | C15: $0.10 / M tokens
A16: g_rate_output | B16: 4e-07 | C16: $0.40 / M tokens
A17: GCP fixed cost per portal
A18: fixed_portal_mo | B18: 0.75 | C18: Firestore storage, Secret Manager, idle Cloud Run — per portal/month
A19: gcp_per_email | B19: 2e-06 | C19: Cloud Run + Cloud Tasks + Firestore ops per email (~0)
A21: DERIVED — per-email cost
A22: Claude cost / email | B22: =(Assumptions!$B$7*Assumptions!$B$11+Assumptions!$B$8*Assumptions!$B$12+Assumptions!$B$9*Assumptions!$B$13) | C22: Cached read + fresh input + output
A23: Gemini cost / email | B23: =((Assumptions!$B$7+Assumptions!$B$8)*Assumptions!$B$15+Assumptions!$B$9*Assumptions!$B$16) | C23: Gemini has no separate cache tier; full input rate
A24: Total marginal $/email (Claude + GCP) | B24: =Assumptions!$B$22+Assumptions!$B$19

Sheet Tiers
A1: PRICING TIERS — base + included bucket + overage
A3: Metric | B3: Starter | C3: Growth | D3: Pro | E3: Enterprise
A4: Base price / month | B4: 20 | C4: 79 | D4: 249 | E4: 750
A5: Included emails | B5: 100 | C5: 1000 | D5: 5000 | E5: 25000
A6: Overage $ / email | B6: 0.15 | C6: 0.1 | D6: 0.06 | E6: 0.035
A7: COGS at full bucket (Claude) | B7: =Assumptions!$B$18+B5*Assumptions!$B$24 | C7: =Assumptions!$B$18+C5*Assumptions!$B$24 | D7: =Assumptions!$B$18+D5*Assumptions!$B$24 | E7: =Assumptions!$B$18+E5*Assumptions!$B$24
A8: Gross margin $ (base, full bucket) | B8: =B4-B7 | C8: =C4-C7 | D8: =D4-D7 | E8: =E4-E7
A9: Gross margin % (base, full bucket) | B9: =IF(B4=0,0,B8/B4) | C9: =IF(C4=0,0,C8/C4) | D9: =IF(D4=0,0,D8/D4) | E9: =IF(E4=0,0,E8/E4)
A10: Effective $/email at cap | B10: =B4/B5 | C10: =C4/C5 | D10: =D4/D5 | E10: =E4/E5
A11: Overage markup vs cost | B11: =B6/Assumptions!$B$24 | C11: =C6/Assumptions!$B$24 | D11: =D6/Assumptions!$B$24 | E11: =E6/Assumptions!$B$24
A13: Green = formula (recalcs from Assumptions). Yellow = editable.
A14: Upgrade trigger: a tier is 'overflowing' once base + overages > next tier's base.

Sheet Provider Sensitivity
A1: PROVIDER COST SENSITIVITY — monthly AI+GCP cost by volume
A3: Emails / month | B3: Claude cost | C3: Gemini cost | D3: Claude $/email | E3: Savings w/ Gemini
A4: 100 | B4: =Assumptions!$B$18+A4*(Assumptions!$B$22+Assumptions!$B$19) | C4: =Assumptions!$B$18+A4*(Assumptions!$B$23+Assumptions!$B$19) | D4: =B4/A4 | E4: =B4-C4
A5: 1000 | B5: =Assumptions!$B$18+A5*(Assumptions!$B$22+Assumptions!$B$19) | C5: =Assumptions!$B$18+A5*(Assumptions!$B$23+Assumptions!$B$19) | D5: =B5/A5 | E5: =B5-C5
A6: 5000 | B6: =Assumptions!$B$18+A6*(Assumptions!$B$22+Assumptions!$B$19) | C6: =Assumptions!$B$18+A6*(Assumptions!$B$23+Assumptions!$B$19) | D6: =B6/A6 | E6: =B6-C6
A7: 10000 | B7: =Assumptions!$B$18+A7*(Assumptions!$B$22+Assumptions!$B$19) | C7: =Assumptions!$B$18+A7*(Assumptions!$B$23+Assumptions!$B$19) | D7: =B7/A7 | E7: =B7-C7
A8: 25000 | B8: =Assumptions!$B$18+A8*(Assumptions!$B$22+Assumptions!$B$19) | C8: =Assumptions!$B$18+A8*(Assumptions!$B$23+Assumptions!$B$19) | D8: =B8/A8 | E8: =B8-C8
A9: 100000 | B9: =Assumptions!$B$18+A9*(Assumptions!$B$22+Assumptions!$B$19) | C9: =Assumptions!$B$18+A9*(Assumptions!$B$23+Assumptions!$B$19) | D9: =B9/A9 | E9: =B9-C9
A10: 1000000 | B10: =Assumptions!$B$18+A10*(Assumptions!$B$22+Assumptions!$B$19) | C10: =Assumptions!$B$18+A10*(Assumptions!$B$23+Assumptions!$B$19) | D10: =B10/A10 | E10: =B10-C10

Sheet Customer Scenario
A1: CUSTOMER SCENARIO CALCULATOR
A2: Edit the yellow inputs to model one customer's monthly bill & your margin.
A4: Base price / month | B4: 79 | C4: what you charge this customer
A5: Included emails (bucket) | B5: 1000
A6: Overage $ / email | B6: 0.1
A7: Actual emails processed | B7: 1500 | C7: their real monthly volume
A9: Overage emails | B9: =MAX(0,B7-B5)
A10: Overage charge | B10: =B9*B6
A11: Customer pays (revenue) | B11: =B4+B10 | C11: base + overage
A12: Your COGS | B12: =Assumptions!$B$18+B7*(Assumptions!$B$22+Assumptions!$B$19) | C12: fixed + Claude+GCP per actual email
A13: Gross profit | B13: =B11-B12
A14: Gross margin % | B14: =IF(B11=0,0,B13/B11)
A15: Profit if run on Gemini | B15: =B11-(Assumptions!$B$18+B7*(Assumptions!$B$23+Assumptions!$B$19)) | C15: same price, cheaper provider
A17: Tip: copy the Customer Scenario block per real client to build a portfolio view.
